aws_solutions_konstruk/core/__init__.py
aws_solutions_konstruk/core/py.typed
aws_solutions_konstruk/core/_jsii/__init__.py
aws_solutions_konstruk/core/_jsii/core@0.8.1.jsii.tgz
aws_solutions_konstruk.core-0.8.1.dist-info/METADATA
aws_solutions_konstruk.core-0.8.1.dist-info/WHEEL
aws_solutions_konstruk.core-0.8.1.dist-info/top_level.txt
aws_solutions_konstruk.core-0.8.1.dist-info/RECORD
