Metadata-Version: 2.1
Name: aws-solutions-konstruk.core
Version: 0.8.1
Summary: Core CDK Construct for patterns library
Home-page: https://github.com/awslabs/aws-solutions-konstruk.git
Author: Amazon Web Services
License: Apache-2.0
Project-URL: Source, https://github.com/awslabs/aws-solutions-konstruk.git
Platform: UNKNOWN
Classifier: Intended Audience :: Developers
Classifier: Operating System :: OS Independent
Classifier: Programming Language :: JavaScript
Classifier: Programming Language :: Python :: 3 :: Only
Classifier: Programming Language :: Python :: 3.6
Classifier: Programming Language :: Python :: 3.7
Classifier: Programming Language :: Python :: 3.8
Classifier: Typing :: Typed
Classifier: License :: OSI Approved
Requires-Python: >=3.6
Requires-Dist: jsii (<2.0.0,>=1.5.0)
Requires-Dist: publication (>=0.0.3)
Requires-Dist: aws-cdk.aws-apigateway (<1.41.0,>=1.40.0)
Requires-Dist: aws-cdk.aws-cloudfront (<1.41.0,>=1.40.0)
Requires-Dist: aws-cdk.aws-cloudwatch (<1.41.0,>=1.40.0)
Requires-Dist: aws-cdk.aws-cognito (<1.41.0,>=1.40.0)
Requires-Dist: aws-cdk.aws-dynamodb (<1.41.0,>=1.40.0)
Requires-Dist: aws-cdk.aws-elasticsearch (<1.41.0,>=1.40.0)
Requires-Dist: aws-cdk.aws-events (<1.41.0,>=1.40.0)
Requires-Dist: aws-cdk.aws-iam (<1.41.0,>=1.40.0)
Requires-Dist: aws-cdk.aws-iot (<1.41.0,>=1.40.0)
Requires-Dist: aws-cdk.aws-kinesis (<1.41.0,>=1.40.0)
Requires-Dist: aws-cdk.aws-kinesisanalytics (<1.41.0,>=1.40.0)
Requires-Dist: aws-cdk.aws-kinesisfirehose (<1.41.0,>=1.40.0)
Requires-Dist: aws-cdk.aws-kms (<1.41.0,>=1.40.0)
Requires-Dist: aws-cdk.aws-lambda (<1.41.0,>=1.40.0)
Requires-Dist: aws-cdk.aws-lambda-event-sources (<1.41.0,>=1.40.0)
Requires-Dist: aws-cdk.aws-logs (<1.41.0,>=1.40.0)
Requires-Dist: aws-cdk.aws-s3 (<1.41.0,>=1.40.0)
Requires-Dist: aws-cdk.aws-sns (<1.41.0,>=1.40.0)
Requires-Dist: aws-cdk.aws-sqs (<1.41.0,>=1.40.0)
Requires-Dist: aws-cdk.core (<1.41.0,>=1.40.0)
